{
  "holdingsTypes": [
    {
      "id": "03c9c400-b9e3-4a07-ac0e-05ab470233ed",
      "name": "Monograph",
      "source": "folio",
      "metadata": {
        "createdDate": "2021-09-08T17:38:18.901+00:00",
        "createdByUserId": "ae65dd95-3ee2-4d1e-808b-c53ad8b5037d",
        "updatedDate": "2021-09-08T17:38:18.901+00:00",
        "updatedByUserId": "ae65dd95-3ee2-4d1e-808b-c53ad8b5037d"
      }
    },
    {
      "id": "e6da6c98-6dd0-41bc-8b4b-cfd4bbd9c3ae",
      "name": "Serial",
      "source": "folio",
      "metadata": {
        "createdDate": "2021-09-08T17:38:18.902+00:00",
        "createdByUserId": "ae65dd95-3ee2-4d1e-808b-c53ad8b5037d",
        "updatedDate": "2021-09-08T17:38:18.902+00:00",
        "updatedByUserId": "ae65dd95-3ee2-4d1e-808b-c53ad8b5037d"
      }
    },
    {
      "id": "dc35d0ae-e877-488b-8e97-6e41444e6d0a",
      "name": "Multi-part monograph",
      "source": "folio",
      "metadata": {
        "createdDate": "2021-09-08T17:38:18.906+00:00",
        "createdByUserId": "ae65dd95-3ee2-4d1e-808b-c53ad8b5037d",
        "updatedDate": "2021-09-08T17:38:18.906+00:00",
        "updatedByUserId": "ae65dd95-3ee2-4d1e-808b-c53ad8b5037d"
      }
    },
    {
      "id": "996f93e2-5b5e-4cf2-9168-33ced1f95eed",
      "name": "Electronic",
      "source": "folio",
      "metadata": {
        "createdDate": "2021-09-08T17:38:18.911+00:00",
        "createdByUserId": "ae65dd95-3ee2-4d1e-808b-c53ad8b5037d",
        "updatedDate": "2021-09-08T17:38:18.911+00:00",
        "updatedByUserId": "ae65dd95-3ee2-4d1e-808b-c53ad8b5037d"
      }
    },
    {
      "id": "0c422f92-0f4d-4d32-8cbe-390ebc33a3e5",
      "name": "Physical",
      "source": "folio",
      "metadata": {
        "createdDate": "2021-09-08T17:38:18.917+00:00",
        "createdByUserId": "ae65dd95-3ee2-4d1e-808b-c53ad8b5037d",
        "updatedDate": "2021-09-08T17:38:18.917+00:00",
        "updatedByUserId": "ae65dd95-3ee2-4d1e-808b-c53ad8b5037d"
      }
    },
    {
      "id": "bf2f0b2d-6e47-4d72-93b8-1c2962aa6f0b",
      "name": "unmapped",
      "source": "local",
      "metadata": {
        "createdDate": "2021-11-20T21:25:02.010+00:00",
        "createdByUserId": "26287f46-96bb-4297-8672-2340fc3325d5",
        "updatedDate": "2021-11-26T17:21:28.595+00:00",
        "updatedByUserId": "4593c990-50b0-499f-86f1-d9e362a1369d"
      }
    }
  ],
  "totalRecords": 6
}